_foo.cpython-38-x86_64-linux-gnu.so
pyronn_layers/__init__.py
pyronn_layers/python/__init__.py
pyronn_layers/python/ops/__init__.py
pyronn_layers/python/ops/_pyronn_layers_ops.so
pyronn_layers/python/ops/pyronn_layers_ops.py
pyronn_layers-0.1.4.2.dist-info/LICENSE
pyronn_layers-0.1.4.2.dist-info/METADATA
pyronn_layers-0.1.4.2.dist-info/WHEEL
pyronn_layers-0.1.4.2.dist-info/top_level.txt
pyronn_layers-0.1.4.2.dist-info/RECORD
