Metadata-Version: 2.1
Name: pyronn-layers
Version: 0.1.4.2
Summary: PYRO-NN-LAYERS are the kernel implemtations for the known operators.
Home-page: https://github.com/csyben/PYRO-NN-Layers
Author: Christopher Syben
Author-email: christopher.syben@fau.de
License: Apache 2.0
Platform: UNKNOWN
Classifier: Intended Audience :: Developers
Classifier: Intended Audience :: Education
Classifier: Intended Audience :: Science/Research
Classifier: License :: OSI Approved :: Apache Software License
Classifier: Programming Language :: Python :: 3.6
Classifier: Programming Language :: Python :: 3.7
Classifier: Programming Language :: Python :: 3.8
Classifier: Topic :: Scientific/Engineering :: Mathematics
Classifier: Topic :: Software Development :: Libraries :: Python Modules
Classifier: Topic :: Software Development :: Libraries
Requires-Python: >=3.6
Requires-Dist: tensorflow (>=2.3.0)
